radiozilla/__init__.py
radiozilla/api/__init__.py
radiozilla/api/browsers.py
radiozilla/datatypes.py
radiozilla/decorators/__init__.py
radiozilla/decorators/memoizations.py
radiozilla/defaults.py
radiozilla/radios.py
radiozilla/structs/__init__.py
radiozilla/structs/codecs.py
radiozilla/structs/countries.py
radiozilla/structs/countrycodes.py
radiozilla/structs/languages.py
radiozilla/structs/states.py
radiozilla/structs/stationchecks.py
radiozilla/structs/stationchecksteps.py
radiozilla/structs/stationclicks.py
radiozilla/structs/stations.py
radiozilla/structs/tags.py
radiozilla-1.0.0.dist-info/LICENSE
radiozilla-1.0.0.dist-info/METADATA
radiozilla-1.0.0.dist-info/WHEEL
radiozilla-1.0.0.dist-info/RECORD
